factiva/core/__init__.py
factiva/core/__version__.py
factiva/core/apikeyuser.py
factiva/core/log.py
factiva/core/stream_response.py
factiva/core/streamuser.py
factiva/core/auth/__init__.py
factiva/core/auth/oauthuser.py
factiva/core/auth/userkey.py
factiva/core/const/__init__.py
factiva/core/const/errors.py
factiva/core/dicts/__init__.py
factiva/core/dicts/factiva-countries.csv
factiva/core/dicts/industries-hrchy.csv
factiva/core/dicts/regions-hrchy.csv
factiva/core/req/__init__.py
factiva/core/tools/__init__.py
factiva/core/tools/files.py
factiva/helper/__init__.py
factiva_core-0.2.5.dist-info/LICENSE
factiva_core-0.2.5.dist-info/METADATA
factiva_core-0.2.5.dist-info/WHEEL
factiva_core-0.2.5.dist-info/top_level.txt
factiva_core-0.2.5.dist-info/RECORD
