Metadata-Version: 2.1
Name: factiva-core
Version: 0.2.5
Summary: Python package with root definitions and dictionaries, to support other functional packages.
Home-page: https://developer.dowjones.com/
Author: Dow Jones Customer Engineers
Author-email: customer.solutions@dowjones.com
License: MIT
Project-URL: GitHub, https://github.com/dowjones/factiva-core-python
Project-URL: Documentation, https://factiva-core-python.readthedocs.io/
Project-URL: Bug Tracker, https://github.com/dowjones/factiva-core-python/issues
Keywords: news,factiva
Classifier: Development Status :: 4 - Beta
Classifier: Intended Audience :: Science/Research
Classifier: Intended Audience :: Financial and Insurance Industry
Classifier: Operating System :: OS Independent
Classifier: Topic :: Office/Business :: News/Diary
Classifier: Topic :: Office/Business :: Financial :: Investment
Classifier: Topic :: Scientific/Engineering :: Artificial Intelligence
Classifier: License :: OSI Approved :: MIT License
Classifier: Programming Language :: Python :: 3.7
Classifier: Programming Language :: Python :: 3.8
Classifier: Programming Language :: Python :: 3.9
Classifier: Programming Language :: Python :: 3.10
Requires-Python: >=3.7
License-File: LICENSE
Requires-Dist: requests
Requires-Dist: pandas
Requires-Dist: numpy
Requires-Dist: google-cloud-pubsub
Requires-Dist: fastavro
